genetic_algorithm_pytorch/__init__.py
genetic_algorithm_pytorch/ga.py
genetic_algorithm_pytorch-0.0.1.dist-info/METADATA
genetic_algorithm_pytorch-0.0.1.dist-info/WHEEL
genetic_algorithm_pytorch-0.0.1.dist-info/licenses/LICENSE
genetic_algorithm_pytorch-0.0.1.dist-info/RECORD
