Metadata-Version: 2.4
Name: genetic-algorithm-pytorch
Version: 0.0.1
Summary: MMDiT
Project-URL: Homepage, https://pypi.org/project/genetic-algorithm-pytorch/
Project-URL: Repository, https://github.com/lucidrains/genetic-algorithm-pytorch
Author-email: Phil Wang <lucidrains@gmail.com>
License: MIT License
License-File: LICENSE
Keywords: artificial intelligence,genetic algorithms
Classifier: Development Status :: 4 - Beta
Classifier: Intended Audience :: Developers
Classifier: License :: OSI Approved :: MIT License
Classifier: Programming Language :: Python :: 3.9
Classifier: Topic :: Scientific/Engineering :: Artificial Intelligence
Requires-Python: >=3.9
Requires-Dist: einops>=0.8.0
Requires-Dist: einx>=0.3.0
Requires-Dist: torch>=2.0
Provides-Extra: examples
Provides-Extra: test
Requires-Dist: pytest; extra == 'test'
